gym_so100/__init__.py
gym_so100/assets/Base.stl
gym_so100/assets/Base_Motor.stl
gym_so100/assets/Fixed_Jaw.stl
gym_so100/assets/Fixed_Jaw_Collision_1.stl
gym_so100/assets/Fixed_Jaw_Collision_2.stl
gym_so100/assets/Fixed_Jaw_Motor.stl
gym_so100/assets/Lower_Arm.stl
gym_so100/assets/Lower_Arm_Motor.stl
gym_so100/assets/Moving_Jaw.stl
gym_so100/assets/Moving_Jaw_Collision_1.stl
gym_so100/assets/Moving_Jaw_Collision_2.stl
gym_so100/assets/Moving_Jaw_Collision_3.stl
gym_so100/assets/Rotation_Pitch.stl
gym_so100/assets/Rotation_Pitch_Motor.stl
gym_so100/assets/Upper_Arm.stl
gym_so100/assets/Upper_Arm_Motor.stl
gym_so100/assets/Wrist_Pitch_Roll.stl
gym_so100/assets/Wrist_Pitch_Roll_Motor.stl
gym_so100/assets/bimanual_end_effector_insertion.xml
gym_so100/assets/bimanual_end_effector_transfer_cube.xml
gym_so100/assets/bimanual_insertion.xml
gym_so100/assets/bimanual_transfer_cube.xml
gym_so100/assets/scene.xml
gym_so100/assets/so_arm100_dependencies.xml
gym_so100/assets/so_arm100_left.xml
gym_so100/assets/so_arm100_right.xml
gym_so100/assets/tabletop.stl
gym_so100/constants.py
gym_so100/env.py
gym_so100/policy.py
gym_so100/tasks/bimanual.py
gym_so100/tasks/sim.py
gym_so100/tasks/sim_end_effector.py
gym_so100/utils.py
gym_so100-0.1.2.dist-info/LICENSE
gym_so100-0.1.2.dist-info/METADATA
gym_so100-0.1.2.dist-info/WHEEL
gym_so100-0.1.2.dist-info/RECORD
