Metadata-Version: 2.1
Name: gym-so100
Version: 0.1.2
Summary: A gym environment for SO100 robot
License: Apache-2.0
Keywords: robotics,deep,reinforcement,learning,so100,environment,gym,gymnasium,dm-control,mujoco
Author: Xiaoxuan Liu
Author-email: xiaoxuan.liu.work@gmail.com
Requires-Python: >=3.10,<4.0
Classifier: Development Status :: 3 - Alpha
Classifier: Intended Audience :: Developers
Classifier: License :: OSI Approved :: Apache Software License
Classifier: Programming Language :: Python :: 3
Classifier: Programming Language :: Python :: 3.10
Classifier: Programming Language :: Python :: 3.11
Classifier: Programming Language :: Python :: 3.12
Classifier: Programming Language :: Python :: 3.13
Classifier: Topic :: Software Development :: Build Tools
Provides-Extra: dev
Provides-Extra: test
Requires-Dist: debugpy (>=1.8.1) ; extra == "dev"
Requires-Dist: dm-control (>=1.0.14)
Requires-Dist: gymnasium (>=0.29.1)
Requires-Dist: imageio-ffmpeg (>=0.5.1)
Requires-Dist: imageio[ffmpeg] (>=2.34.0)
Requires-Dist: matplotlib (>=3.10.0)
Requires-Dist: mujoco (>=3.0)
Requires-Dist: pre-commit (>=3.7.0) ; extra == "dev"
Requires-Dist: pyquaternion (>=0.9.9)
Requires-Dist: pytest (>=8.1.0) ; extra == "test"
Requires-Dist: pytest-cov (>=5.0.0) ; extra == "test"
